abacura/__init__.py
abacura/abacura.py
abacura/config.py
abacura/css/abacura.css
abacura/mud/__init__.py
abacura/mud/logger.py
abacura/mud/session.py
abacura/mud/options/__init__.py
abacura/mud/options/msdp.py
abacura/mud/options/ttype.py
abacura/plugins/__init__.py
abacura/plugins/context_manager.py
abacura/plugins/director.py
abacura/plugins/loader.py
abacura/plugins/sound.py
abacura/plugins/telnet.py
abacura/plugins/actions/__init__.py
abacura/plugins/actions/helper.py
abacura/plugins/aliases/__init__.py
abacura/plugins/aliases/helper.py
abacura/plugins/aliases/manager.py
abacura/plugins/commands/__init__.py
abacura/plugins/commands/command_helper.py
abacura/plugins/commands/helper.py
abacura/plugins/commands/workers.py
abacura/plugins/debug/__init__.py
abacura/plugins/debug/plugin_helper.py
abacura/plugins/debug/profile.py
abacura/plugins/debug/pycharm.py
abacura/plugins/demo/__init__.py
abacura/plugins/demo/demo.py
abacura/plugins/demo/meta.py
abacura/plugins/events/__init__.py
abacura/plugins/events/events.py
abacura/plugins/exec/PythonExecutor.py
abacura/plugins/exec/__init__.py
abacura/plugins/session/__init__.py
abacura/plugins/session/helper.py
abacura/plugins/session/log_search.py
abacura/plugins/task_queue/__init__.py
abacura/plugins/task_queue/runner.py
abacura/plugins/tickers/__init__.py
abacura/plugins/tickers/helper.py
abacura/screens/__init__.py
abacura/utils/__init__.py
abacura/utils/fifo_buffer.py
abacura/utils/meval.py
abacura/utils/profiler.py
abacura/utils/pycharm.py
abacura/utils/renderables.py
abacura/utils/ring_buffer.py
abacura/utils/timer.py
abacura/widgets/__init__.py
abacura/widgets/_inspector.py
abacura/widgets/_rich_image.py
abacura/widgets/commslog.py
abacura/widgets/debug.py
abacura/widgets/footer.py
abacura/widgets/image_widget.py
abacura/widgets/inputbar.py
abacura/widgets/menu_bar.py
abacura/widgets/plot.py
abacura/widgets/resizehandle.py
abacura/widgets/sidebar.py
abacura-0.0.15.dist-info/METADATA
abacura-0.0.15.dist-info/WHEEL
abacura-0.0.15.dist-info/entry_points.txt
abacura-0.0.15.dist-info/top_level.txt
abacura-0.0.15.dist-info/RECORD
