Metadata-Version: 2.1
Name: abacura
Version: 0.0.15
Summary: Multi-session MUD client written in Python with Textual library
License: Proprietary
Classifier: License :: Other/Proprietary License
Requires-Python: >3.10
Requires-Dist: asynctelnet ~=0.2.5
Requires-Dist: click ==8.1.3
Requires-Dist: textual ~=0.35.0
Requires-Dist: tomlkit ==0.11.8
Requires-Dist: numpy
Requires-Dist: plotext
Requires-Dist: pillow
